[
  {
    "model": "rareapi.post",
    "pk": 1,
    "fields": {
        "rare_user_id": 1,
        "category_id": 2,
        "title": "I ate a sandwich.",
        "publication_date": "2021-1-28",
        "image_url": "https://www.sogoodblog.com/wp-content/uploads/2011/02/2511598079_a0636fb93b.jpg",
        "content": "everybody loves sanwiches, that's why everybody eats them. It's just stuff between bread.",
        "approved": 1
      }
  },
  {
    "model": "rareapi.post",
    "pk": 2,
    "fields": {
        "rare_user_id": 2,
        "category_id": 3,
        "title": "I'm healthy now.",
        "publication_date": "2023-11-04",
        "image_url": "https://leaf.nutrisystem.com/wp-content/uploads/2017/01/ThinkstockPhotos-177313400.jpg",
        "content": "I don't eat sandwiches and candy all day like these dog-gone kids. It's attrocious what they're doing.",
        "approved": 1
      }
  },
  {
    "model": "rareapi.post",
    "pk": 3,
    "fields": {
        "rare_user_id": 3,
        "category_id": 1,
        "title": "I don't do anything anymore.",
        "publication_date": "2019-08-07",
        "image_url": "https://nypost.com/wp-content/uploads/sites/2/2017/01/170104-man-finds-brick-wall-feature.jpg?quality=75&strip=all",
        "content": "I'm not bored. I'm mostly just sick of doing stuff. I have a great chair and I know every detail of the wall in front of me.",
        "approved": 1
      }
  }
]
